[
  {
    "contents": "add macroexp",
    "history": [
      ["created", "2025-04-25T06:11:41.368654294+08:00"],
      ["deleted", "2025-04-25T17:34:29.890372910+08:00"]
    ]
  },
  {
    "contents": "add statements",
    "history": [
      ["created", "2025-04-25T06:12:18.983245848+08:00"],
      ["deleted", "2025-04-25T17:34:29.890378210+08:00"]
    ]
  },
  {
    "contents": "add types",
    "history": [
      ["created", "2025-04-25T06:11:24.549515088+08:00"],
      ["deleted", "2025-04-25T17:34:29.890381135+08:00"]
    ]
  },
  {
    "contents": "add string literal",
    "history": [
      ["created", "2025-04-25T06:12:58.612570642+08:00"],
      ["deleted", "2025-04-25T17:34:29.890383360+08:00"]
    ]
  }
]
